fastwings/__init__.py
fastwings/app.py
fastwings/compile_package.py
fastwings/config.py
fastwings/error_code.py
fastwings/exception.py
fastwings/model.py
fastwings/response.py
fastwings/schema.py
fastwings/timer.py
fastwings/authen/__init__.py
fastwings/authen/basic.py
fastwings/authen/bearer.py
fastwings/connection/__init__.py
fastwings/connection/sql_async_conn.py
fastwings/connection/sql_conn.py
fastwings/crud/__init__.py
fastwings/crud/sql_async_repo.py
fastwings/crud/sql_query_builder.py
fastwings/crud/sql_repo.py
fastwings/logger/__init__.py
fastwings/logger/filter.py
fastwings/logger/formatter/__init__.py
fastwings/logger/formatter/json_formatter.py
fastwings/logger/handler/__init__.py
fastwings/logger/handler/file_handler.py
fastwings/logger/handler/gg_chat_handler.py
fastwings/logger/handler/logstash_handler.py
fastwings/logger/handler/stdout_handler.py
fastwings/middleware/__init__.py
fastwings/middleware/common_handler.py
fastwings/middleware/exception_handler.py
fastwings/pattern/__init__.py
fastwings/pattern/singleton.py
fastwings-0.0.18.dist-info/licenses/LICENSE.txt
fastwings-0.0.18.dist-info/METADATA
fastwings-0.0.18.dist-info/WHEEL
fastwings-0.0.18.dist-info/top_level.txt
fastwings-0.0.18.dist-info/RECORD
